con2020/Model.py
con2020/Test.py
con2020/_Analytic.py
con2020/_Integrate.py
con2020/_Switcher.py
con2020/__init__.py
con2020/lmic.py
con2020/__data/testdata.sav
con2020-1.2.9.dist-info/METADATA
con2020-1.2.9.dist-info/WHEEL
con2020-1.2.9.dist-info/top_level.txt
con2020-1.2.9.dist-info/RECORD
