Metadata-Version: 2.1
Name: con2020
Version: 1.2.9
Summary: Python module for the Connerney 2020 model.
Home-page: https://github.com/gabbyprovan/con2020
Author: Gabby Provan and Matt James
Author-email: gp31@leicester.ac.uk
Classifier: Programming Language :: Python :: 3
Classifier: License :: OSI Approved :: MIT License
Classifier: Operating System :: POSIX
Requires-Dist: numpy
Requires-Dist: scipy
Requires-Dist: matplotlib
